ipynb/__init__.py
ipynb/utils.py
ipynb/fs/__init__.py
ipynb/fs/finder.py
ipynb/fs/defs/__init__.py
ipynb/fs/full/__init__.py
ipynb/setup/__init__.py
ipynb-0.5.1.dist-info/DESCRIPTION.rst
ipynb-0.5.1.dist-info/METADATA
ipynb-0.5.1.dist-info/RECORD
ipynb-0.5.1.dist-info/WHEEL
ipynb-0.5.1.dist-info/metadata.json
ipynb-0.5.1.dist-info/top_level.txt
